{
  "sourceId": "yt_-hdA-SHqUqQ",
  "sourceName": "매경 월가월부",
  "sourceType": "video",
  "title": "[홍장원의 불앤베어] 이란 \"미국 협상은 완전히 헛소리\" 진실은 무엇인가",
  "url": "https://www.youtube.com/watch?v=-hdA-SHqUqQ",
  "rawText": "자, 오늘 증시가 상당히 반등하는 날이었습니다. 그건 뭐 명백하게 일한 사태가 좀 해결될 기미가 보였기 때문입니다. 타임라인으로 정리를 좀 해 보자면은 어제도 정리해 드렸지만 지난 며칠간 상황을 정리를 해 보면 아, 지난 아, 금요일이었죠. 어, 이거 저희가 다 전해드린 내용입니다. 지난 금요일 작전 축소가 될 수 있다. 트럼프 대통령이 언급을 했고 어, 토요일에는 악시오스가 보도를 했습니다. 쿠시너와 위트코프 주도로 백악관이 협상 준비 초기에 들어갔다는 그런 내용이었습니다. 그리고 그 뒤에 몇 시간 이후에 트럼프 대통령의 48시간 최후 통첩이 있었고요. 이것도 뭐 다 보내 드렸죠, 저희가. 그리고 이제 그 이후에 이란의 불바다 선언 너희가 우리 에너지 공격하면은 우리도 주변국 에너지 시설 다 공격할 거다. 이렇게 불받아 선언이 있었고 그리고 이제 48시간 최후 통첩의 데드라인이 얼마 남지 않은 상황에서 오늘 오전 결국 트럼프 대통령의 타코가 다시 나왔습니다. 내용은 이거였습니다. 미국과 이란이 지난 이틀간 중동에서의 적대 행위를 완전히 종식하기 위한 매우 생산적인 대화를 나눴음을 기쁘게 알린다.이 이 건설적인 대화와 분위기와 기조를 바탕으로 대화는 이번 주 내내 개솔될 예정이고 나는 전쟁부에 이러한 발전소 및 에너지 인프라에 대한 모든 공격을 5일간 연기하도록 지시했다. 이런 내용이었습니다. 자,이 내용이 나오니까 이란에서는 급반발 합니다. 대표적으로이란 파르스 통신. 미국과 직접적인 소통은 물론 중제자를 통한 소통도 전혀 없었다. 이렇게 보도를 했고요. 또 다른 또 타스님 통신은 미국과 진행 중인 협상은 없고 호르무즈 헤업은 전쟁 이전 상태로 돌아가지 않을 것이다. 이렇게 했습니다. 또 이란의 통신을 종합해 보자면 트럼프가 후퇴한 것이다. 우리가 불발선 하니까 트럼프가 겁먹고 물러난 것이다. 트럼프의 발언은 폭등하는 에너지 가격을 낮추려는 정치적인 수사이자 군사 계획 실행을 위한 시간 벌기에 불과하다 이렇게 주장을 했습니다. 그리고 최근에 나온이 중앙사령부 대변인 얘기를 보시면은 우리는 더 오늘도 공격을 했다. 기만적인 미국 대통령의 모순들 행태는 우리를 방심하게 만들지 못한다. 그래서 텔 아비브와 하이파이도 공격을 했고 실제 오늘 이스라엘도 어 공격을 이어갔습니다. 이렇게 모스의 뉴스가 나오면서 오늘 장초반 유가와 증시 상당히 출렁거리는 모습이었습니다. 지금 보시면은 유가가 타코가 나오자마자 쭉 내려갔다가 이제 꾸준히 이제 반등하는 그런 모습. 하지만 결론만 보자면 그렇죠. 상당한 증시 상승 마감. 그리고 국제가는 매우 급격하게 떨어지는 그런 모습으로 마감을 했습니다. 여기에 대해서 트럼프는 이란이 전쟁을 해결하기를 원한다고 말했다. 그들은 합의를 원하고 우리는 그것을 해낼 것이다. 우리나 희망한다. 이제이라는 미국과 동맹국에 의한 위협을 끝낼 체스를 잡았고 우리는 그들이 그 기회를 잡기를 원한다. 그러면서 협상은 토요일에 시작됐다고 어 말했습니다. 그리고 지금 악시우스 보도를 조금 보시면은 지금 중제국들이 중제국들이 어 이슬라마드이 파키스탄에 있는 도시입니다. 여기서 이제 회의를 소집하려 하고 있다고 보도를 했습니다. 그래서 이란측에서는 의외 의장 갈리바프 그다음에 어 그의 그 어떤 동료들 그리고 미국 측에서는 이미 악시오스 보도로 나왔던 위트 커프 쿠슈너 그리고 가능하면 령까지 참석하는 회담을 이번 주 안에 열려한다는 어 그런 내용으로 보도를 하고 있습니다. 그래서 지금 보시면은 어 이집트 외무장관도 위트코프 또 아라그치 둘 다 난 통화를 했다. 파키스탄, 터키, 카타로, 여무장관 통화를 했는데 지금이 여러 명과 통화를 쭉 하면서이 분쟁을 좀 빨리 해결하자. 이런 거의 중요성을 강조했다. 그러니까 파키스탄, 이집트 그리고 카타르 뭐 이런 나라들이 지금 중간에 확실히 조율를 하고 있다. 이런 거는 지금 보도로 정황이 나오고 있습니다. 그래서 아, 지금 벌어지는 일하자면은 가능성은네 개 중에 하난데요. 어, 하나는 이제 트럼프의 일방적 주장이다. 이건 일한측의 얘기죠. 두 번째는 트럼프가 시간 끌기 하는 거다. 이것도 이란측의 주장이라고 볼 수 있습니다. 그리고 세 번째는 이란이 거짓말을 하고 있는 것이다. 사실은 협상에 들어갔음에도 우리가 협상을 하고 있지 않다고 거짓말 하는 거다. 그리고네 번째 시나리오는 이란도 지금 이제 지위부가 괴멸돼 가지고 누가 지위부인지가 명확하지 않다. 누군가는 전쟁을 원하고 누군가는 휴전을 원한다. 이렇게 분열되어 있을 수 있다는 것이죠. 근데 지금 조금 이런 얘기가 나올 수밖에 없는 이유가 트럼프조차도 지금 이란의 협상 당사자가 누군지를 밝히지 않고 있습니다. 트럼프 말하기로 우리는 내가 이란에서 가장 존경받는다고 생각하는 인물과 협상 중이고 지금 최고 지도자 모즈타바에는 아니다. 그에게는 연락이 없었다. 이런 얘기가 나오고 있습니다. 또 트럼프영은 누군지를 밝히지 않겠다. 왜냐면은 그러다가 그가 죽으니까 이렇게 얘기를 하거든요. 그래서 그럼 지금 그 언론에서 누구와 협상하고 있는지 막 추측이 나오겠죠. 가장 유력한 사람은 지금 악시오스 등에 따르면은이 갈리바프입니다. 갈리바프 이런 의회 의장인데요. 어제도 제가 설명드렸죠. 어이 사람은 과거 혁명 수비대를 이끌던 강경파고요. 어제 지금 유가 말고 미국 국채를 공격해 가지고 국채 금리를 높이게 만들자. 이런 얘기를 했던 그런 당사자이기도 합니다. 그래서 가장 유력한 후보자는이 갈리바프인데 아 문제는 갈리바프가 아니라고 쓰고 있습니다. 나 아니다. 미국과 어떠한 협상도 이루어진 적이 없고 이거는 가짜 뉴스를 활용해서 금융 시장 유가 시장을 조작하고 미국이 이스라엘이 자기네들 이제 수령해서 탈출하려고 지금 흘리는 것이다. 이렇게 하고 있습니다. 그러니까 모든 것이 사실 좀 회색 제대에 있는 것이죠. 하지만 어여튼 오늘의 결과는 증시의 상승 그리고 유가의 하락입니다. 다만 지금 방권이 되고 있는 채권금 보시면은 이거는 좀 뭐 덜 떨어졌는데 시장 일가액에서는 아 트럼프가 진정 물러나는 것이냐 이런 것에 대한 의문은 좀 남아 있다 이렇게 볼 수 있지만 하지만 뭐가 아 진실이고 뭐가 정의인지 이런 걸 떠나서 그리고 저희 월걸부 채널은이 제테크 채널이기 때문에 뭐가 정의인지를 논의하는 그런 채널은 아닙니다. 투자 채널이기 때문인데요. 여튼 투자 관점에서 봤을 때 트럼프의 말 한마디는 이란의 그것보다 훨씬 더 금융 시장에 미치는 파장이 압도적으로 크다. 이런 점을 다시 한번 알 수 있게 하고 있습니다. 일각에서는 지난해 4월이 트럼프의 엄청난 탁코가 나왔던 중국과의 회담을 떠올리기도 합니다. 왜냐면 이때도 막 둘이 그냥 치킨 게임을 하다가 갑자기 미국 트럼프가 글을 올립니다. 아 협상이 잘되고 있다. 수요일인가 그랬어요. 4월 뭐 초였죠. 그래서 막 증시가 막 SP에 거의 10% 뜨고 막 그랬는데 그러니까 중국이이 트럼프가 밝힌 몇 시간 이후에 공식 채널을 통해서 아니 그 뭔 얘기냐 이거 그 가짜 뉴스다. 협상이 이뤄진 적이 없다. 미국이 소설 쓰는 거다. 이렇게 공식 채널을 통해서 얘기를 했거든요. 그런데 결국 그로부터 몇 주 뒤인 어 5월에 끝내 미국과 중국은 합의를 어 했습니다. 이때도 중국이 부인하니까 트럼프는 아니다. 우리 얼마 전에 만났어. 뭐 누군지는 밝힐 수가 없는데 우리 만났어. 이렇게 얘기를 했거든요. 지금과 어떻게 보면 굉장히 닮아 있는 거죠. 중은 당시도 부인했고 이번에도 이란을 부인했고 트럼프는 협상 대상자를 그때도 밝히지 않고 이번에도 밝히지 않고 있습니다. 요러으로 닮은 점이 있는데 결국 이런 걸 보면은 어 진실이 무엇이든지간에 어 최강대군은 어쩔 수 없이 미국이고요. 미국이 체를 잡고 끌고 가면은 아무리 중국이라도 어느 정도는 끌려갈 수밖에 없다. 이런 식의 냉엄한 국제 질서를 보여 주는 거 같기도 한데 이때 중국과 난리 일하는 뭐 엄청난 타협을 입었죠. 최고 지도자가 미사일 맞고 죽기도 했고요. 그래서 이때와 또 상황이 완전히 같다고 볼 수 없지만 여튼 이번에도 결국은 트럼프가 얘기하는 대로 다 흘러가게 될지 한번 또 상황을 지켜보는 시간을 가져보도록 하겠습니다. 자, 오늘 준비한 영상 이것으로 마무리하고요. 올걸보 구독과 좋아요 많은 사랑 부탁드립니다. 감사합니다.",
  "metadata": {
    "channelName": "매경 월가월부",
    "publishedAt": "2026-03-23T22:49:37+00:00"
  },
  "collectedAt": "2026-03-24T15:00:11.666967+09:00"
}